libnova/__init__.py
libnova/__main__.py
libnova/log/__init__.py
libnova/log/log.py
libnova/pwn/__init__.py
libnova/pwn/conf.py
libnova/pwn/pwn.py
libnova/struct/__init__.py
libnova/struct/rangemap.py
libnova/typ/__init__.py
libnova/typ/comparable.py
libnova-0.1.14.dist-info/WHEEL
libnova-0.1.14.dist-info/METADATA
libnova-0.1.14.dist-info/RECORD
