Metadata-Version: 2.1
Name: libnova
Version: 0.1.14
Summary: Personal python batteries libary -- mostly binary analysis, exploitation.
Home-page: https://github.com/novafacing/libnova.git
Author: novafacing
Author-email: rowanbhart@gmail.com
Requires-Python: ==3.8.10
Classifier: Programming Language :: Python :: 3
Requires-Dist: coloredlogs (>=15.0.1,<16.0.0)
Requires-Dist: pwntools (>=4.7.0,<5.0.0)
